AUTHORS
LICENSE
MANIFEST.in
README.rst
setup.py
sphinxcontrib/__init__.py
sphinxcontrib/embedly.py
sphinxcontrib_embedly.egg-info/PKG-INFO
sphinxcontrib_embedly.egg-info/SOURCES.txt
sphinxcontrib_embedly.egg-info/dependency_links.txt
sphinxcontrib_embedly.egg-info/namespace_packages.txt
sphinxcontrib_embedly.egg-info/not-zip-safe
sphinxcontrib_embedly.egg-info/requires.txt
sphinxcontrib_embedly.egg-info/top_level.txt